candyLumerty
