Metadata-Version: 1.1
Name: candyLumerty
Version: 0.6
Summary: Test version
Home-page: https://github.com/Corbie325/candyLumerty
Author: Artem
Author-email: prototype22rus@mail.ru
License: MIT
Download-URL: https://github.com/Corbie325/candyLumerty/archive/refs/tags/v_06.tar.gz
Keywords: CandyLumerty
Platform: UNKNOWN
Classifier: Development Status :: 3 - Alpha
Classifier: Intended Audience :: Developers
Classifier: Topic :: Software Development :: Build Tools
Classifier: License :: OSI Approved :: MIT License
Classifier: Programming Language :: Python :: 3
Classifier: Programming Language :: Python :: 3.4
Classifier: Programming Language :: Python :: 3.5
Classifier: Programming Language :: Python :: 3.6
